s1aux/__init__.py
s1aux/_core.py
s1aux/v1_05/__init__.py
s1aux/v1_05/itc.py
s1aux/v1_05/s1_object_types.py
s1aux/v1_05/scf.py
s1aux/v1_06/__init__.py
s1aux/v1_06/itc.py
s1aux/v1_06/s1_object_types.py
s1aux/v2_10/__init__.py
s1aux/v2_10/cal.py
s1aux/v2_10/ins.py
s1aux/v2_10/pp1.py
s1aux/v2_10/pp2.py
s1aux/v2_10/s1_object_types.py
s1aux/v3_03/__init__.py
s1aux/v3_03/ins.py
s1aux/v3_03/pp1.py
s1aux/v3_03/pp2.py
s1aux/v3_03/s1_object_types.py
s1aux/v3_07/__init__.py
s1aux/v3_07/ins.py
s1aux/v3_07/pp1.py
s1aux/v3_07/s1_object_types.py
s1aux/v3_08/__init__.py
s1aux/v3_08/pp2.py
s1aux/v3_08/s1_object_types.py
s1aux/v3_09/__init__.py
s1aux/v3_09/pp2.py
s1aux/v3_09/s1_object_types.py
s1aux/v3_12/__init__.py
s1aux/v3_12/pp1.py
s1aux/v3_12/s1_object_types.py
s1aux-0.9.dist-info/licenses/LICENSE
s1aux-0.9.dist-info/METADATA
s1aux-0.9.dist-info/WHEEL
s1aux-0.9.dist-info/top_level.txt
s1aux-0.9.dist-info/RECORD
