Metadata-Version: 2.4
Name: s1aux
Version: 0.9
Summary: Sentinel-1 auxiliary (AUX) products reader.
Author-email: Antonio Valentino <antonio.valentino@tiscali.it>
License: Apache-2.0
Project-URL: Homepage, https://github.com/avalentino/s1aux
Project-URL: Documentation, https://github.com/avalentino/s1aux/blob/main/README.rst
Project-URL: Repository, https://github.com/avalentino/s1aux.git
Project-URL: Changelog, https://github.com/avalentino/s1aux/blob/main/NEWS.rst
Project-URL: Issues, https://github.com/avalentino/s1aux/issues
Keywords: satellite,sentinel-1,esa,sar,sar-mpc
Classifier: Development Status :: 4 - Beta
Classifier: Intended Audience :: Science/Research
Classifier: Operating System :: OS Independent
Classifier: Programming Language :: Python :: 3
Classifier: Programming Language :: Python :: 3 :: Only
Classifier: Topic :: Scientific/Engineering
Classifier: Topic :: Utilities
Requires-Python: >=3.10
License-File: LICENSE
Requires-Dist: xsdata
Dynamic: license-file
